README.md
setup.cfg
setup.py
pandacan.egg-info/PKG-INFO
pandacan.egg-info/SOURCES.txt
pandacan.egg-info/dependency_links.txt
pandacan.egg-info/requires.txt
pandacan.egg-info/top_level.txt
python/__init__.py
python/dfu.py
python/esptool.py
python/flash_release.py
python/isotp.py
python/serial.py
python/uds.py
python/update.py