Metadata-Version: 1.1
Name: pandacan
Version: 0.0.9
Summary: Code powering the comma.ai panda
Home-page: https://github.com/commaai/panda
Author: comma.ai
Author-email: UNKNOWN
License: MIT
Platform: any
Classifier: Development Status :: 2 - Pre-Alpha
Classifier: Natural Language :: English
Classifier: Programming Language :: Python :: 2
Classifier: Programming Language :: Python :: 3
Classifier: Topic :: System :: Hardware
